hyra_client-1.0.1.dist-info/licenses/LICENSE
hyra_sdk/__init__.py
hyra_sdk/client.py
hyra_sdk/abis/model-registry.json
hyra_sdk/abis/pool-factory.json
hyra_sdk/abis/pool-router.json
hyra_sdk/abis/pool-viewer.json
hyra_sdk/abis/task-pool.json
hyra_client-1.0.1.dist-info/METADATA
hyra_client-1.0.1.dist-info/WHEEL
hyra_client-1.0.1.dist-info/entry_points.txt
hyra_client-1.0.1.dist-info/top_level.txt
hyra_client-1.0.1.dist-info/RECORD
