Metadata-Version: 2.4
Name: hyra-client
Version: 1.0.1
Summary: A comprehensive Python SDK for the Hyra decentralized task marketplace
Author-email: Hyra Network <dev@hyra.network>
Maintainer-email: Hyra Network <dev@hyra.network>
License: MIT
Project-URL: Homepage, https://github.com/hyra-network/hyra-python-sdk
Project-URL: Documentation, https://docs.hyra.network
Project-URL: Repository, https://github.com/hyra-network/hyra-python-sdk
Project-URL: Bug Tracker, https://github.com/hyra-network/hyra-python-sdk/issues
Project-URL: Discord, https://discord.gg/hyra
Keywords: hyra,blockchain,ai,tasks,marketplace,zkp,zero-knowledge-proof
Classifier: Development Status :: 4 - Beta
Classifier: Intended Audience :: Developers
Classifier: Topic :: Software Development :: Libraries :: Python Modules
Classifier: Topic :: Scientific/Engineering :: Artificial Intelligence
Classifier: License :: OSI Approved :: MIT License
Classifier: Programming Language :: Python :: 3
Classifier: Programming Language :: Python :: 3.8
Classifier: Programming Language :: Python :: 3.9
Classifier: Programming Language :: Python :: 3.10
Classifier: Programming Language :: Python :: 3.11
Classifier: Programming Language :: Python :: 3.12
Classifier: Operating System :: OS Independent
Requires-Python: >=3.8
License-File: LICENSE
Requires-Dist: web3>=7.0.0
Requires-Dist: python-dotenv>=1.0.0
Requires-Dist: zkp-rust-client
Requires-Dist: requests>=2.28.2
Provides-Extra: dev
Requires-Dist: pytest>=6.0; extra == "dev"
Requires-Dist: black; extra == "dev"
Requires-Dist: flake8; extra == "dev"
Requires-Dist: mypy; extra == "dev"
Dynamic: license-file
